{"4bc6d588f360ef3b943fdc2d": {"category": "Mall", "raw_source": {"verified": false, "name": "Centria | \u0633\u0646\u062a\u0631\u064a\u0627", "url": "http://www.centria.com.sa", "hereNow": {"count": 6, "groups": [{"count": 6, "items": [], "type": "others", "name": "Other people here"}], "summary": "6 people are here"}, "contact": {"phone": "+966112161111", "formattedPhone": "+966 11 216 1111"}, "location": {"city": "\u0627\u0644\u0631\u064a\u0627\u0636", "cc": "SA", "country": "\u0627\u0644\u0645\u0645\u0644\u0643\u0629 \u0627\u0644\u0639\u0631\u0628\u064a\u0629 \u0627\u0644\u0633\u0639\u0648\u062f\u064a\u0629", "state": "\u0645\u0646\u0637\u0642\u0629 \u0627\u0644\u0631\u064a\u0627\u0636\u200e", "formattedAddress": ["Tahlia St. (Olaya St.)", "\u0627\u0644\u0631\u064a\u0627\u0636", "\u0627\u0644\u0645\u0645\u0644\u0643\u0629 \u0627\u0644\u0639\u0631\u0628\u064a\u0629 \u0627\u0644\u0633\u0639\u0648\u062f\u064a\u0629"], "crossStreet": "Olaya St.", "address": "Tahlia St.", "lat": 24.697129175717542, "lng": 46.68392300605773}, "stats": {"tipCount": 317, "checkinsCount": 69171, "usersCount": 22643}, "id": "4bc6d588f360ef3b943fdc2d", "categories": [{"pluralName": "Malls", "primary": true, "name": "Mall", "shortName": "Mall", "id": "4bf58dd8d48988d1fd941735", "icon": {"prefix": "https://ss3.4sqi.net/img/categories_v2/shops/mall_", "suffix": ".png"}}]}, "data_source": "foursquare_trending", "here_now": 6, "place_id": "4bc6d588f360ef3b943fdc2d", "lon": 46.68392300605773, "users_count": 22643, "content": "Centria | \u0633\u0646\u062a\u0631\u064a\u0627", "data_point": "none", "time": "2015-10-09 10:29:59.783030", "lat": 24.697129175717542, "checkins": 69171}, "4e3c350fa809ba757bf8fa7d": {"category": "Coffee Shop", "raw_source": {"verified": true, "name": "Starbucks | \u0633\u062a\u0627\u0631\u0628\u0643\u0633", "url": "http://mena.starbucks.com", "storeId": "", "hereNow": {"count": 10, "groups": [{"count": 10, "items": [], "type": "others", "name": "Other people here"}], "summary": "10 people are here"}, "allowMenuUrlEdit": true, "contact": {"phone": "+966112051161", "facebookUsername": "StarbucksMiddleEast", "facebook": "297276700389130", "formattedPhone": "+966 11 205 1161", "facebookName": "Starbucks Middle East"}, "location": {"city": "\u0627\u0644\u0631\u064a\u0627\u0636", "cc": "SA", "country": "\u0627\u0644\u0645\u0645\u0644\u0643\u0629 \u0627\u0644\u0639\u0631\u0628\u064a\u0629 \u0627\u0644\u0633\u0639\u0648\u062f\u064a\u0629", "state": "\u0645\u0646\u0637\u0642\u0629 \u0627\u0644\u0631\u064a\u0627\u0636\u200e", "formattedAddress": ["King Abdullah Rd.", "\u0627\u0644\u0631\u064a\u0627\u0636", "\u0627\u0644\u0645\u0645\u0644\u0643\u0629 \u0627\u0644\u0639\u0631\u0628\u064a\u0629 \u0627\u0644\u0633\u0639\u0648\u062f\u064a\u0629"], "address": "King Abdullah Rd.", "lat": 24.730561735168433, "lng": 46.67179067364015}, "stats": {"tipCount": 231, "checkinsCount": 22154, "usersCount": 6252}, "id": "4e3c350fa809ba757bf8fa7d", "categories": [{"pluralName": "Coffee Shops", "primary": true, "name": "Coffee Shop", "shortName": "Coffee Shop", "id": "4bf58dd8d48988d1e0931735", "icon": {"prefix": "https://ss3.4sqi.net/img/categories_v2/food/coffeeshop_", "suffix": ".png"}}]}, "data_source": "foursquare_trending", "here_now": 10, "place_id": "4e3c350fa809ba757bf8fa7d", "lon": 46.67179067364015, "users_count": 6252, "content": "Starbucks | \u0633\u062a\u0627\u0631\u0628\u0643\u0633", "data_point": "none", "time": "2015-10-09 10:29:59.782998", "lat": 24.730561735168433, "checkins": 22154}, "4bb60acd46d4a5932198c5c0": {"category": "Mall", "raw_source": {"verified": false, "name": "Panorama Mall | \u0628\u0627\u0646\u0648\u0631\u0627\u0645\u0627 \u0645\u0648\u0644", "url": "http://www.panorama-mall.com", "hereNow": {"count": 5, "groups": [{"count": 5, "items": [], "type": "others", "name": "Other people here"}], "summary": "5 people are here"}, "contact": {"twitter": "panorama_mall"}, "location": {"city": "\u0627\u0644\u0631\u064a\u0627\u0636", "cc": "SA", "country": "\u0627\u0644\u0645\u0645\u0644\u0643\u0629 \u0627\u0644\u0639\u0631\u0628\u064a\u0629 \u0627\u0644\u0633\u0639\u0648\u062f\u064a\u0629", "state": "\u0645\u0646\u0637\u0642\u0629 \u0627\u0644\u0631\u064a\u0627\u0636\u200e", "formattedAddress": ["Takhassusi St. (Tahlia St.)", "\u0627\u0644\u0631\u064a\u0627\u0636", "\u0627\u0644\u0645\u0645\u0644\u0643\u0629 \u0627\u0644\u0639\u0631\u0628\u064a\u0629 \u0627\u0644\u0633\u0639\u0648\u062f\u064a\u0629"], "crossStreet": "Tahlia St.", "address": "Takhassusi St.", "lat": 24.69209095771737, "lng": 46.66980080509867}, "stats": {"tipCount": 321, "checkinsCount": 57786, "usersCount": 18883}, "id": "4bb60acd46d4a5932198c5c0", "categories": [{"pluralName": "Malls", "primary": true, "name": "Mall", "shortName": "Mall", "id": "4bf58dd8d48988d1fd941735", "icon": {"prefix": "https://ss3.4sqi.net/img/categories_v2/shops/mall_", "suffix": ".png"}}]}, "data_source": "foursquare_trending", "here_now": 5, "place_id": "4bb60acd46d4a5932198c5c0", "lon": 46.66980080509867, "users_count": 18883, "content": "Panorama Mall | \u0628\u0627\u0646\u0648\u0631\u0627\u0645\u0627 \u0645\u0648\u0644", "data_point": "none", "time": "2015-10-09 10:29:59.783122", "lat": 24.69209095771737, "checkins": 57786}, "4b73f92df964a5202ec22de3": {"category": "Mall", "raw_source": {"verified": false, "name": "Hayat Mall | \u062d\u064a\u0627\u0629 \u0645\u0648\u0644", "url": "http://www.hayat-mall.com", "hereNow": {"count": 5, "groups": [{"count": 5, "items": [], "type": "others", "name": "Other people here"}], "summary": "5 people are here"}, "contact": {}, "location": {"city": "\u0627\u0644\u0631\u064a\u0627\u0636", "cc": "SA", "country": "\u0627\u0644\u0645\u0645\u0644\u0643\u0629 \u0627\u0644\u0639\u0631\u0628\u064a\u0629 \u0627\u0644\u0633\u0639\u0648\u062f\u064a\u0629", "state": "\u0645\u0646\u0637\u0642\u0629 \u0627\u0644\u0631\u064a\u0627\u0636\u200e", "formattedAddress": ["King Abdulaziz Rd.", "\u0627\u0644\u0631\u064a\u0627\u0636", "\u0627\u0644\u0645\u0645\u0644\u0643\u0629 \u0627\u0644\u0639\u0631\u0628\u064a\u0629 \u0627\u0644\u0633\u0639\u0648\u062f\u064a\u0629"], "address": "King Abdulaziz Rd.", "lat": 24.74293381026252, "lng": 46.67992115020752}, "stats": {"tipCount": 225, "checkinsCount": 31556, "usersCount": 11978}, "id": "4b73f92df964a5202ec22de3", "categories": [{"pluralName": "Malls", "primary": true, "name": "Mall", "shortName": "Mall", "id": "4bf58dd8d48988d1fd941735", "icon": {"prefix": "https://ss3.4sqi.net/img/categories_v2/shops/mall_", "suffix": ".png"}}]}, "data_source": "foursquare_trending", "here_now": 5, "place_id": "4b73f92df964a5202ec22de3", "lon": 46.67992115020752, "users_count": 11978, "content": "Hayat Mall | \u062d\u064a\u0627\u0629 \u0645\u0648\u0644", "data_point": "none", "time": "2015-10-09 10:31:00.201875", "lat": 24.74293381026252, "checkins": 31556}, "4b7707bff964a52018762ee3": {"category": "Mall", "raw_source": {"verified": false, "name": "Kingdom Centre | \u0645\u0631\u0643\u0632 \u0627\u0644\u0645\u0645\u0644\u0643\u0629", "url": "http://www.kingdomcenter.com.sa", "hereNow": {"count": 5, "groups": [{"count": 5, "items": [], "type": "others", "name": "Other people here"}], "summary": "5 people are here"}, "contact": {"phone": "+966112112222", "formattedPhone": "+966 11 211 2222"}, "location": {"city": "\u0627\u0644\u0631\u064a\u0627\u0636", "cc": "SA", "country": "\u0627\u0644\u0645\u0645\u0644\u0643\u0629 \u0627\u0644\u0639\u0631\u0628\u064a\u0629 \u0627\u0644\u0633\u0639\u0648\u062f\u064a\u0629", "postalCode": "111321", "state": "\u0645\u0646\u0637\u0642\u0629 \u0627\u0644\u0631\u064a\u0627\u0636\u200e", "formattedAddress": ["Olaya St (Orouba St)", "\u0627\u0644\u0631\u064a\u0627\u0636 111321", "\u0627\u0644\u0645\u0645\u0644\u0643\u0629 \u0627\u0644\u0639\u0631\u0628\u064a\u0629 \u0627\u0644\u0633\u0639\u0648\u062f\u064a\u0629"], "crossStreet": "Orouba St", "address": "Olaya St", "lat": 24.711632551668487, "lng": 46.674771308898926}, "stats": {"tipCount": 293, "checkinsCount": 87305, "usersCount": 23346}, "id": "4b7707bff964a52018762ee3", "categories": [{"pluralName": "Malls", "primary": true, "name": "Mall", "shortName": "Mall", "id": "4bf58dd8d48988d1fd941735", "icon": {"prefix": "https://ss3.4sqi.net/img/categories_v2/shops/mall_", "suffix": ".png"}}]}, "data_source": "foursquare_trending", "here_now": 5, "place_id": "4b7707bff964a52018762ee3", "lon": 46.674771308898926, "users_count": 23346, "content": "Kingdom Centre | \u0645\u0631\u0643\u0632 \u0627\u0644\u0645\u0645\u0644\u0643\u0629", "data_point": "none", "time": "2015-10-09 10:31:00.201823", "lat": 24.711632551668487, "checkins": 87305}, "53f4ac57498e3bd97f602bb3": {"category": "Japanese Restaurant", "raw_source": {"verified": true, "name": "Nozomi \u0646\u0648\u0632\u0648\u0645\u064a", "url": "http://www.nozomisaudi.com", "hereNow": {"count": 5, "groups": [{"count": 5, "items": [], "type": "others", "name": "Other people here"}], "summary": "5 people are here"}, "allowMenuUrlEdit": true, "contact": {"phone": "+966114152213", "formattedPhone": "+966 11 415 2213"}, "location": {"city": "\u0627\u0644\u0631\u064a\u0627\u0636", "cc": "SA", "country": "\u0627\u0644\u0645\u0645\u0644\u0643\u0629 \u0627\u0644\u0639\u0631\u0628\u064a\u0629 \u0627\u0644\u0633\u0639\u0648\u062f\u064a\u0629", "state": "\u0645\u0646\u0637\u0642\u0629 \u0627\u0644\u0631\u064a\u0627\u0636\u200e", "formattedAddress": ["Dabab Street", "\u0627\u0644\u0631\u064a\u0627\u0636", "\u0627\u0644\u0645\u0645\u0644\u0643\u0629 \u0627\u0644\u0639\u0631\u0628\u064a\u0629 \u0627\u0644\u0633\u0639\u0648\u062f\u064a\u0629"], "address": "Dabab Street", "lat": 24.700151804733018, "lng": 46.70468212694794}, "venuePage": {"id": "96529352"}, "stats": {"tipCount": 516, "checkinsCount": 5644, "usersCount": 3375}, "id": "53f4ac57498e3bd97f602bb3", "categories": [{"pluralName": "Japanese Restaurants", "primary": true, "name": "Japanese Restaurant", "shortName": "Japanese", "id": "4bf58dd8d48988d111941735", "icon": {"prefix": "https://ss3.4sqi.net/img/categories_v2/food/japanese_", "suffix": ".png"}}]}, "data_source": "foursquare_trending", "here_now": 5, "place_id": "53f4ac57498e3bd97f602bb3", "lon": 46.70468212694794, "users_count": 3375, "content": "Nozomi \u0646\u0648\u0632\u0648\u0645\u064a", "data_point": "none", "time": "2015-10-09 10:29:59.783091", "lat": 24.700151804733018, "checkins": 5644}, "5558568a498e982e87bccaa0": {"category": "Furniture / Home Store", "raw_source": {"verified": false, "name": "ABYAT  | \u0623\u0628\u064a\u0627\u062a", "url": "http://www.abyatonline.com", "hereNow": {"count": 6, "groups": [{"count": 6, "items": [], "type": "others", "name": "Other people here"}], "summary": "6 people are here"}, "allowMenuUrlEdit": true, "contact": {"phone": "+9668001215555", "twitter": "abyat", "formattedPhone": "+966 800 121 5555"}, "location": {"city": "\u0627\u0644\u0631\u064a\u0627\u0636", "cc": "SA", "country": "\u0627\u0644\u0645\u0645\u0644\u0643\u0629 \u0627\u0644\u0639\u0631\u0628\u064a\u0629 \u0627\u0644\u0633\u0639\u0648\u062f\u064a\u0629", "state": "\u0645\u0646\u0637\u0642\u0629 \u0627\u0644\u0631\u064a\u0627\u0636\u200e", "formattedAddress": ["3207 Nortern Ring Branch Rd, Al Ghadir", "Riyadh 12284", "Saudi Arabia", "\u0627\u0644\u0631\u064a\u0627\u0636", "\u0627\u0644\u0645\u0645\u0644\u0643\u0629 \u0627\u0644\u0639\u0631\u0628\u064a\u0629 \u0627\u0644\u0633\u0639\u0648\u062f\u064a\u0629"], "address": "3207 Nortern Ring Branch Rd, Al Ghadir\nRiyadh 12284\nSaudi Arabia", "lat": 24.768253730580184, "lng": 46.66128581732236}, "stats": {"tipCount": 59, "checkinsCount": 1285, "usersCount": 1056}, "id": "5558568a498e982e87bccaa0", "categories": [{"pluralName": "Furniture / Home Stores", "primary": true, "name": "Furniture / Home Store", "shortName": "Furniture / Home", "id": "4bf58dd8d48988d1f8941735", "icon": {"prefix": "https://ss3.4sqi.net/img/categories_v2/shops/furniture_", "suffix": ".png"}}]}, "data_source": "foursquare_trending", "here_now": 6, "place_id": "5558568a498e982e87bccaa0", "lon": 46.66128581732236, "users_count": 1056, "content": "ABYAT  | \u0623\u0628\u064a\u0627\u062a", "data_point": "none", "time": "2015-10-09 10:29:59.783060", "lat": 24.768253730580184, "checkins": 1285}, "4d624f7b5b276dcb21c82dc6": {"category": "Coffee Shop", "raw_source": {"verified": true, "name": "Starbucks | \u0633\u062a\u0627\u0631\u0628\u0643\u0633", "url": "http://mena.starbucks.com", "storeId": "", "hereNow": {"count": 7, "groups": [{"count": 7, "items": [], "type": "others", "name": "Other people here"}], "summary": "7 people are here"}, "allowMenuUrlEdit": true, "contact": {"facebookUsername": "StarbucksMiddleEast", "facebook": "297276700389130", "facebookName": "Starbucks Middle East"}, "location": {"city": "\u0627\u0644\u0631\u064a\u0627\u0636", "cc": "SA", "country": "\u0627\u0644\u0645\u0645\u0644\u0643\u0629 \u0627\u0644\u0639\u0631\u0628\u064a\u0629 \u0627\u0644\u0633\u0639\u0648\u062f\u064a\u0629", "state": "\u0645\u0646\u0637\u0642\u0629 \u0627\u0644\u0631\u064a\u0627\u0636\u200e", "formattedAddress": ["Khurais Road", "\u0627\u0644\u0631\u064a\u0627\u0636", "\u0627\u0644\u0645\u0645\u0644\u0643\u0629 \u0627\u0644\u0639\u0631\u0628\u064a\u0629 \u0627\u0644\u0633\u0639\u0648\u062f\u064a\u0629"], "address": "Khurais Road", "lat": 24.722445217786188, "lng": 46.775117808171416}, "stats": {"tipCount": 206, "checkinsCount": 17533, "usersCount": 3781}, "id": "4d624f7b5b276dcb21c82dc6", "categories": [{"pluralName": "Coffee Shops", "primary": true, "name": "Coffee Shop", "shortName": "Coffee Shop", "id": "4bf58dd8d48988d1e0931735", "icon": {"prefix": "https://ss3.4sqi.net/img/categories_v2/food/coffeeshop_", "suffix": ".png"}}]}, "data_source": "foursquare_trending", "here_now": 7, "place_id": "4d624f7b5b276dcb21c82dc6", "lon": 46.775117808171416, "users_count": 3781, "content": "Starbucks | \u0633\u062a\u0627\u0631\u0628\u0643\u0633", "data_point": "none", "time": "2015-10-09 10:29:59.783019", "lat": 24.722445217786188, "checkins": 17533}, "505034cde4b05606210c0868": {"category": "Street", "raw_source": {"verified": false, "name": "Tahlia Street | \u0634\u0627\u0631\u0639 \u0627\u0644\u062a\u062d\u0644\u064a\u0629", "hereNow": {"count": 6, "groups": [{"count": 6, "items": [], "type": "others", "name": "Other people here"}], "summary": "6 people are here"}, "contact": {}, "location": {"city": "\u0627\u0644\u0631\u064a\u0627\u0636", "neighborhood": "Sulaymaniyah", "cc": "SA", "country": "\u0627\u0644\u0645\u0645\u0644\u0643\u0629 \u0627\u0644\u0639\u0631\u0628\u064a\u0629 \u0627\u0644\u0633\u0639\u0648\u062f\u064a\u0629", "state": "\u0645\u0646\u0637\u0642\u0629 \u0627\u0644\u0631\u064a\u0627\u0636\u200e", "formattedAddress": ["Prince Muhammad Ibn Abdulaziz Street", "\u0627\u0644\u0631\u064a\u0627\u0636", "\u0627\u0644\u0645\u0645\u0644\u0643\u0629 \u0627\u0644\u0639\u0631\u0628\u064a\u0629 \u0627\u0644\u0633\u0639\u0648\u062f\u064a\u0629"], "address": "Prince Muhammad Ibn Abdulaziz Street", "lat": 24.699114354060562, "lng": 46.69029269800889}, "stats": {"tipCount": 543, "checkinsCount": 130746, "usersCount": 21536}, "id": "505034cde4b05606210c0868", "categories": [{"pluralName": "Streets", "primary": true, "name": "Street", "shortName": "Street", "id": "52f2ab2ebcbc57f1066b8b52", "icon": {"prefix": "https://ss3.4sqi.net/img/categories_v2/travel/highway_", "suffix": ".png"}}]}, "data_source": "foursquare_trending", "here_now": 6, "place_id": "505034cde4b05606210c0868", "lon": 46.69029269800889, "users_count": 21536, "content": "Tahlia Street | \u0634\u0627\u0631\u0639 \u0627\u0644\u062a\u062d\u0644\u064a\u0629", "data_point": "none", "time": "2015-10-09 10:29:59.783050", "lat": 24.699114354060562, "checkins": 130746}, "4f68eb88e4b0b4f7926b1ac8": {"category": "City", "raw_source": {"verified": false, "name": "Riyadh | \u0627\u0644\u0631\u064a\u0627\u0636", "url": "http://www.arriyadh.com", "hereNow": {"count": 6, "groups": [{"count": 6, "items": [], "type": "others", "name": "Other people here"}], "summary": "6 people are here"}, "contact": {}, "location": {"cc": "SA", "country": "\u0627\u0644\u0645\u0645\u0644\u0643\u0629 \u0627\u0644\u0639\u0631\u0628\u064a\u0629 \u0627\u0644\u0633\u0639\u0648\u062f\u064a\u0629", "state": "\u0645\u0646\u0637\u0642\u0629 \u0627\u0644\u0631\u064a\u0627\u0636\u200e", "formattedAddress": ["\u0627\u0644\u0645\u0645\u0644\u0643\u0629 \u0627\u0644\u0639\u0631\u0628\u064a\u0629 \u0627\u0644\u0633\u0639\u0648\u062f\u064a\u0629"], "lat": 24.748681940353553, "lng": 46.70097822280755}, "stats": {"tipCount": 17, "checkinsCount": 43951, "usersCount": 14107}, "id": "4f68eb88e4b0b4f7926b1ac8", "categories": [{"pluralName": "Cities", "primary": true, "name": "City", "shortName": "City", "id": "50aa9e094b90af0d42d5de0d", "icon": {"prefix": "https://ss3.4sqi.net/img/categories_v2/parks_outdoors/neighborhood_", "suffix": ".png"}}]}, "data_source": "foursquare_trending", "here_now": 6, "place_id": "4f68eb88e4b0b4f7926b1ac8", "lon": 46.70097822280755, "users_count": 14107, "content": "Riyadh | \u0627\u0644\u0631\u064a\u0627\u0636", "data_point": "none", "time": "2015-10-09 10:29:59.783040", "lat": 24.748681940353553, "checkins": 43951}, "4e6e352ed1647053b9ff9315": {"category": "Mall", "raw_source": {"verified": false, "name": "Granada Center | \u0645\u0631\u0643\u0632 \u063a\u0631\u0646\u0627\u0637\u0629", "url": "http://www.granadacenter.com.sa", "hereNow": {"count": 8, "groups": [{"count": 8, "items": [], "type": "others", "name": "Other people here"}], "summary": "8 people are here"}, "contact": {"phone": "12534990", "twitter": "granadamall", "formattedPhone": "12534990"}, "location": {"city": "\u0627\u0644\u0631\u064a\u0627\u0636", "cc": "SA", "country": "\u0627\u0644\u0645\u0645\u0644\u0643\u0629 \u0627\u0644\u0639\u0631\u0628\u064a\u0629 \u0627\u0644\u0633\u0639\u0648\u062f\u064a\u0629", "state": "\u0645\u0646\u0637\u0642\u0629 \u0627\u0644\u0631\u064a\u0627\u0636\u200e", "formattedAddress": ["Eastern Ring Rd. (Exit 9)", "\u0627\u0644\u0631\u064a\u0627\u0636", "\u0627\u0644\u0645\u0645\u0644\u0643\u0629 \u0627\u0644\u0639\u0631\u0628\u064a\u0629 \u0627\u0644\u0633\u0639\u0648\u062f\u064a\u0629"], "crossStreet": "Exit 9", "address": "Eastern Ring Rd.", "lat": 24.78089904696122, "lng": 46.73062184925106}, "stats": {"tipCount": 299, "checkinsCount": 40221, "usersCount": 13883}, "id": "4e6e352ed1647053b9ff9315", "categories": [{"pluralName": "Malls", "primary": true, "name": "Mall", "shortName": "Mall", "id": "4bf58dd8d48988d1fd941735", "icon": {"prefix": "https://ss3.4sqi.net/img/categories_v2/shops/mall_", "suffix": ".png"}}]}, "data_source": "foursquare_trending", "here_now": 8, "place_id": "4e6e352ed1647053b9ff9315", "lon": 46.73062184925106, "users_count": 13883, "content": "Granada Center | \u0645\u0631\u0643\u0632 \u063a\u0631\u0646\u0627\u0637\u0629", "data_point": "none", "time": "2015-10-09 10:29:59.783009", "lat": 24.78089904696122, "checkins": 40221}, "528767c111d2a9f79af8cc8a": {"category": "Hotel", "raw_source": {"verified": true, "name": "\u0641\u0646\u062f\u0642 \u0628\u0631\u062c \u0631\u0627\u0641\u0627\u0644 \u0643\u0645\u0628\u064a\u0646\u0633\u0643\u064a | Burj Rafal Hotel Kempinski", "url": "http://www.kempinski.com/en/riyadh/burj-rafal-hotel/welcome/", "hereNow": {"count": 5, "groups": [{"count": 5, "items": [], "type": "others", "name": "Other people here"}], "summary": "5 people are here"}, "allowMenuUrlEdit": true, "contact": {"phone": "+966115117777", "twitter": "burjrafalhotel", "formattedPhone": "+966 11 511 7777"}, "location": {"city": "Riyadh", "cc": "SA", "country": "\u0627\u0644\u0645\u0645\u0644\u0643\u0629 \u0627\u0644\u0639\u0631\u0628\u064a\u0629 \u0627\u0644\u0633\u0639\u0648\u062f\u064a\u0629", "state": "Riayadh", "formattedAddress": ["King Fahd Rd (Imam Saud Bin Faisal St)", "Riyadh", "\u0627\u0644\u0645\u0645\u0644\u0643\u0629 \u0627\u0644\u0639\u0631\u0628\u064a\u0629 \u0627\u0644\u0633\u0639\u0648\u062f\u064a\u0629"], "crossStreet": "Imam Saud Bin Faisal St", "address": "King Fahd Rd", "lat": 24.79235033257607, "lng": 46.63243241079112}, "venuePage": {"id": "102720682"}, "stats": {"tipCount": 228, "checkinsCount": 9768, "usersCount": 5385}, "id": "528767c111d2a9f79af8cc8a", "categories": [{"pluralName": "Hotels", "primary": true, "name": "Hotel", "shortName": "Hotel", "id": "4bf58dd8d48988d1fa931735", "icon": {"prefix": "https://ss3.4sqi.net/img/categories_v2/travel/hotel_", "suffix": ".png"}}]}, "data_source": "foursquare_trending", "here_now": 5, "place_id": "528767c111d2a9f79af8cc8a", "lon": 46.63243241079112, "users_count": 5385, "content": "\u0641\u0646\u062f\u0642 \u0628\u0631\u062c \u0631\u0627\u0641\u0627\u0644 \u0643\u0645\u0628\u064a\u0646\u0633\u0643\u064a | Burj Rafal Hotel Kempinski", "data_point": "none", "time": "2015-10-09 10:29:59.783111", "lat": 24.79235033257607, "checkins": 9768}, "53a47071498e183ecb19e0cf": {"category": "Mall", "raw_source": {"verified": false, "name": "Al Nakheel Mall | \u0627\u0644\u0646\u062e\u064a\u0644 \u0645\u0648\u0644", "url": "http://www.nakheelmall.com", "hereNow": {"count": 14, "groups": [{"count": 14, "items": [], "type": "others", "name": "Other people here"}], "summary": "14 people are here"}, "contact": {}, "location": {"city": "\u0627\u0644\u0631\u064a\u0627\u0636", "cc": "SA", "country": "\u0627\u0644\u0645\u0645\u0644\u0643\u0629 \u0627\u0644\u0639\u0631\u0628\u064a\u0629 \u0627\u0644\u0633\u0639\u0648\u062f\u064a\u0629", "state": "\u0645\u0646\u0637\u0642\u0629 \u0627\u0644\u0631\u064a\u0627\u0636\u200e", "formattedAddress": ["Othman Ibn Affan Rd (Imam Saud Ibn Abdul Aziz Rd.)", "\u0627\u0644\u0631\u064a\u0627\u0636", "\u0627\u0644\u0645\u0645\u0644\u0643\u0629 \u0627\u0644\u0639\u0631\u0628\u064a\u0629 \u0627\u0644\u0633\u0639\u0648\u062f\u064a\u0629"], "crossStreet": "Imam Saud Ibn Abdul Aziz Rd.", "address": "Othman Ibn Affan Rd", "lat": 24.768058419570764, "lng": 46.71471943292468}, "stats": {"tipCount": 299, "checkinsCount": 12412, "usersCount": 5907}, "id": "53a47071498e183ecb19e0cf", "categories": [{"pluralName": "Malls", "primary": true, "name": "Mall", "shortName": "Mall", "id": "4bf58dd8d48988d1fd941735", "icon": {"prefix": "https://ss3.4sqi.net/img/categories_v2/shops/mall_", "suffix": ".png"}}]}, "data_source": "foursquare_trending", "here_now": 14, "place_id": "53a47071498e183ecb19e0cf", "lon": 46.71471943292468, "users_count": 5907, "content": "Al Nakheel Mall | \u0627\u0644\u0646\u062e\u064a\u0644 \u0645\u0648\u0644", "data_point": "none", "time": "2015-10-09 10:29:59.782926", "lat": 24.768058419570764, "checkins": 12412}, "4c3344e266e40f47ecafc78b": {"category": "Bookstore", "raw_source": {"verified": true, "name": "Jarir Bookstore | \u0645\u0643\u062a\u0628\u0629 \u062c\u0631\u064a\u0631", "url": "http://t.co/e8JyHBzC6O", "storeId": "", "hereNow": {"count": 5, "groups": [{"count": 5, "items": [], "type": "others", "name": "Other people here"}], "summary": "5 people are here"}, "allowMenuUrlEdit": true, "contact": {"phone": "+966920000089", "twitter": "jarirbookstore", "formattedPhone": "+966 9200 00089"}, "location": {"city": "\u0627\u0644\u0631\u064a\u0627\u0636", "cc": "SA", "country": "\u0627\u0644\u0645\u0645\u0644\u0643\u0629 \u0627\u0644\u0639\u0631\u0628\u064a\u0629 \u0627\u0644\u0633\u0639\u0648\u062f\u064a\u0629", "state": "\u0645\u0646\u0637\u0642\u0629 \u0627\u0644\u0631\u064a\u0627\u0636\u200e", "formattedAddress": ["Northern Ring Rd. \u0627\u0644\u0637\u0631\u064a\u0642 \u0627\u0644\u062f\u0627\u0626\u0631\u064a \u0627\u0644\u0634\u0645\u0627\u0644\u064a (Exit 5 \u0645\u062e\u0631\u062c \u0665)", "\u0627\u0644\u0631\u064a\u0627\u0636", "\u0627\u0644\u0645\u0645\u0644\u0643\u0629 \u0627\u0644\u0639\u0631\u0628\u064a\u0629 \u0627\u0644\u0633\u0639\u0648\u062f\u064a\u0629"], "crossStreet": "Exit 5 \u0645\u062e\u0631\u062c \u0665", "address": "Northern Ring Rd. \u0627\u0644\u0637\u0631\u064a\u0642 \u0627\u0644\u062f\u0627\u0626\u0631\u064a \u0627\u0644\u0634\u0645\u0627\u0644\u064a", "lat": 24.772435401919438, "lng": 46.67296011202005}, "stats": {"tipCount": 88, "checkinsCount": 12147, "usersCount": 5277}, "id": "4c3344e266e40f47ecafc78b", "categories": [{"pluralName": "Bookstores", "primary": true, "name": "Bookstore", "shortName": "Bookstore", "id": "4bf58dd8d48988d114951735", "icon": {"prefix": "https://ss3.4sqi.net/img/categories_v2/shops/bookstore_", "suffix": ".png"}}]}, "data_source": "foursquare_trending", "here_now": 5, "place_id": "4c3344e266e40f47ecafc78b", "lon": 46.67296011202005, "users_count": 5277, "content": "Jarir Bookstore | \u0645\u0643\u062a\u0628\u0629 \u062c\u0631\u064a\u0631", "data_point": "none", "time": "2015-10-09 10:29:59.783071", "lat": 24.772435401919438, "checkins": 12147}, "4b4838e9f964a520544a26e3": {"category": "Coffee Shop", "raw_source": {"verified": true, "name": "Starbucks | \u0633\u062a\u0627\u0631\u0628\u0643\u0633", "url": "http://mena.starbucks.com", "storeId": "", "hereNow": {"count": 12, "groups": [{"count": 12, "items": [], "type": "others", "name": "Other people here"}], "summary": "12 people are here"}, "allowMenuUrlEdit": true, "contact": {"phone": "+966114889301", "facebookUsername": "StarbucksMiddleEast", "facebook": "297276700389130", "formattedPhone": "+966 11 488 9301", "facebookName": "Starbucks Middle East"}, "location": {"city": "\u0627\u0644\u0631\u064a\u0627\u0636", "cc": "SA", "country": "\u0627\u0644\u0645\u0645\u0644\u0643\u0629 \u0627\u0644\u0639\u0631\u0628\u064a\u0629 \u0627\u0644\u0633\u0639\u0648\u062f\u064a\u0629", "state": "\u0645\u0646\u0637\u0642\u0629 \u0627\u0644\u0631\u064a\u0627\u0636\u200e", "formattedAddress": ["Takhassusi St. (Mecca Rd)", "\u0627\u0644\u0631\u064a\u0627\u0636", "\u0627\u0644\u0645\u0645\u0644\u0643\u0629 \u0627\u0644\u0639\u0631\u0628\u064a\u0629 \u0627\u0644\u0633\u0639\u0648\u062f\u064a\u0629"], "crossStreet": "Mecca Rd", "address": "Takhassusi St.", "lat": 24.676143, "lng": 46.67635}, "stats": {"tipCount": 172, "checkinsCount": 24286, "usersCount": 4630}, "id": "4b4838e9f964a520544a26e3", "categories": [{"pluralName": "Coffee Shops", "primary": true, "name": "Coffee Shop", "shortName": "Coffee Shop", "id": "4bf58dd8d48988d1e0931735", "icon": {"prefix": "https://ss3.4sqi.net/img/categories_v2/food/coffeeshop_", "suffix": ".png"}}]}, "data_source": "foursquare_trending", "here_now": 12, "place_id": "4b4838e9f964a520544a26e3", "lon": 46.67635, "users_count": 4630, "content": "Starbucks | \u0633\u062a\u0627\u0631\u0628\u0643\u0633", "data_point": "none", "time": "2015-10-09 10:29:59.782975", "lat": 24.676143, "checkins": 24286}, "54d0fb58498e0840028024ba": {"category": "Gym", "raw_source": {"verified": false, "name": "NuYu Gym", "url": "http://nuyu-ksa.com", "hereNow": {"count": 5, "groups": [{"count": 5, "items": [], "type": "others", "name": "Other people here"}], "summary": "5 people are here"}, "allowMenuUrlEdit": true, "contact": {"phone": "+966551933060", "formattedPhone": "+966 55 193 3060"}, "location": {"lat": 24.745065238265482, "cc": "SA", "lng": 46.72413565959907, "formattedAddress": ["\u0627\u0644\u0645\u0645\u0644\u0643\u0629 \u0627\u0644\u0639\u0631\u0628\u064a\u0629 \u0627\u0644\u0633\u0639\u0648\u062f\u064a\u0629"], "country": "\u0627\u0644\u0645\u0645\u0644\u0643\u0629 \u0627\u0644\u0639\u0631\u0628\u064a\u0629 \u0627\u0644\u0633\u0639\u0648\u062f\u064a\u0629"}, "stats": {"tipCount": 14, "checkinsCount": 1412, "usersCount": 154}, "id": "54d0fb58498e0840028024ba", "categories": [{"pluralName": "Gyms", "primary": true, "name": "Gym", "shortName": "Gym", "id": "4bf58dd8d48988d176941735", "icon": {"prefix": "https://ss3.4sqi.net/img/categories_v2/building/gym_", "suffix": ".png"}}]}, "data_source": "foursquare_trending", "here_now": 5, "place_id": "54d0fb58498e0840028024ba", "lon": 46.72413565959907, "users_count": 154, "content": "NuYu Gym", "data_point": "none", "time": "2015-10-09 10:29:59.783081", "lat": 24.745065238265482, "checkins": 1412}, "4e0ef3a752b1b27c1b8bcd2a": {"category": "Middle Eastern Restaurant", "raw_source": {"verified": false, "name": "Karam Beirut | \u0643\u0631\u0645 \u0628\u064a\u0631\u0648\u062a", "hereNow": {"count": 5, "groups": [{"count": 5, "items": [], "type": "others", "name": "Other people here"}], "summary": "5 people are here"}, "allowMenuUrlEdit": true, "contact": {"phone": "+966114161717", "formattedPhone": "+966 11 416 1717"}, "location": {"city": "\u0627\u0644\u0631\u064a\u0627\u0636", "cc": "SA", "country": "\u0627\u0644\u0645\u0645\u0644\u0643\u0629 \u0627\u0644\u0639\u0631\u0628\u064a\u0629 \u0627\u0644\u0633\u0639\u0648\u062f\u064a\u0629", "state": "\u0645\u0646\u0637\u0642\u0629 \u0627\u0644\u0631\u064a\u0627\u0636\u200e", "formattedAddress": ["Tahlia St.", "\u0627\u0644\u0631\u064a\u0627\u0636", "\u0627\u0644\u0645\u0645\u0644\u0643\u0629 \u0627\u0644\u0639\u0631\u0628\u064a\u0629 \u0627\u0644\u0633\u0639\u0648\u062f\u064a\u0629"], "address": "Tahlia St.", "lat": 24.703752562097204, "lng": 46.70199264064044}, "stats": {"tipCount": 355, "checkinsCount": 11465, "usersCount": 7653}, "id": "4e0ef3a752b1b27c1b8bcd2a", "categories": [{"pluralName": "Middle Eastern Restaurants", "primary": true, "name": "Middle Eastern Restaurant", "shortName": "Middle Eastern", "id": "4bf58dd8d48988d115941735", "icon": {"prefix": "https://ss3.4sqi.net/img/categories_v2/food/middleeastern_", "suffix": ".png"}}]}, "data_source": "foursquare_trending", "here_now": 5, "place_id": "4e0ef3a752b1b27c1b8bcd2a", "lon": 46.70199264064044, "users_count": 7653, "content": "Karam Beirut | \u0643\u0631\u0645 \u0628\u064a\u0631\u0648\u062a", "data_point": "none", "time": "2015-10-09 10:29:59.783101", "lat": 24.703752562097204, "checkins": 11465}, "4c7c1f55566db60c31c34c0e": {"category": "Coffee Shop", "raw_source": {"verified": true, "name": "Starbucks | \u0633\u062a\u0627\u0631\u0628\u0643\u0633", "url": "http://mena.starbucks.com", "storeId": "", "hereNow": {"count": 5, "groups": [{"count": 5, "items": [], "type": "others", "name": "Other people here"}], "summary": "5 people are here"}, "allowMenuUrlEdit": true, "contact": {"phone": "+966112490498", "facebookUsername": "StarbucksMiddleEast", "facebook": "297276700389130", "formattedPhone": "+966 11 249 0498", "facebookName": "Starbucks Middle East"}, "location": {"city": "\u0627\u0644\u0631\u064a\u0627\u0636", "cc": "SA", "country": "\u0627\u0644\u0645\u0645\u0644\u0643\u0629 \u0627\u0644\u0639\u0631\u0628\u064a\u0629 \u0627\u0644\u0633\u0639\u0648\u062f\u064a\u0629", "state": "\u0645\u0646\u0637\u0642\u0629 \u0627\u0644\u0631\u064a\u0627\u0636\u200e", "formattedAddress": ["King Abdullah Rd. Ext 10 (King Abdullah Rd.)", "\u0627\u0644\u0631\u064a\u0627\u0636", "\u0627\u0644\u0645\u0645\u0644\u0643\u0629 \u0627\u0644\u0639\u0631\u0628\u064a\u0629 \u0627\u0644\u0633\u0639\u0648\u062f\u064a\u0629"], "crossStreet": "King Abdullah Rd.", "address": "King Abdullah Rd. Ext 10", "lat": 24.76702499667982, "lng": 46.75593734344663}, "stats": {"tipCount": 130, "checkinsCount": 10613, "usersCount": 3200}, "id": "4c7c1f55566db60c31c34c0e", "categories": [{"pluralName": "Coffee Shops", "primary": true, "name": "Coffee Shop", "shortName": "Coffee Shop", "id": "4bf58dd8d48988d1e0931735", "icon": {"prefix": "https://ss3.4sqi.net/img/categories_v2/food/coffeeshop_", "suffix": ".png"}}]}, "data_source": "foursquare_trending", "here_now": 5, "place_id": "4c7c1f55566db60c31c34c0e", "lon": 46.75593734344663, "users_count": 3200, "content": "Starbucks | \u0633\u062a\u0627\u0631\u0628\u0643\u0633", "data_point": "none", "time": "2015-10-09 10:33:31.253608", "lat": 24.76702499667982, "checkins": 10613}}